{"version":3,"commands":{},"prefs":{"websites.hyperlinkAuditingEnabled":{"initialValue":{},"precedenceList":[{"id":"adnauseam@rednoise.org","installDate":1762457610043,"value":false,"enabled":true}]},"network.networkPredictionEnabled":{"initialValue":{"network.prefetch-next":false,"network.http.speculative-parallel-limit":0,"network.dns.disablePrefetch":true},"precedenceList":[{"id":"adnauseam@rednoise.org","installDate":1762457610043,"value":false,"enabled":true}]}},"default_search":{},"url_overrides":{}}